liblaf/tangerine/__init__.py
liblaf/tangerine/__init__.pyi
liblaf/tangerine/__main__.py
liblaf/tangerine/_version.py
liblaf/tangerine/_version.pyi
liblaf/tangerine/py.typed
liblaf/tangerine/cli/__init__.py
liblaf/tangerine/cli/__init__.pyi
liblaf/tangerine/cli/_main.py
liblaf/tangerine/cli/invoke.py
liblaf/tangerine/cli/parse.py
liblaf/tangerine/core/__init__.py
liblaf/tangerine/core/__init__.pyi
liblaf/tangerine/core/constants.py
liblaf/tangerine/core/environment.py
liblaf/tangerine/core/template.py
liblaf/tangerine/plugin/__init__.py
liblaf/tangerine/plugin/__init__.pyi
liblaf/tangerine/plugin/_github.py
liblaf/tangerine/plugin/_text.py
liblaf/tangerine/templates/badges/python.md
liblaf/tangerine/templates/projects/copier.md
liblaf/tangerine/templates/projects/fruits.md
liblaf/tangerine/utils/__init__.py
liblaf/tangerine/utils/__init__.pyi
liblaf/tangerine/utils/_app_dirs.py
liblaf_tangerine-0.4.1.dist-info/METADATA
liblaf_tangerine-0.4.1.dist-info/WHEEL
liblaf_tangerine-0.4.1.dist-info/entry_points.txt
liblaf_tangerine-0.4.1.dist-info/RECORD
