Metadata-Version: 2.4
Name: liblaf-tangerine
Version: 0.4.1
Summary: 🍊 Squeeze dynamic content into your files with Tangerine's template magic.
Project-URL: Changelog, https://github.com/liblaf/tangerine/blob/main/CHANGELOG.md
Project-URL: Documentation, https://liblaf.github.io/tangerine/
Project-URL: Funding, https://github.com/liblaf/tangerine?sponsor=1
Project-URL: Homepage, https://github.com/liblaf/tangerine
Project-URL: Issue Tracker, https://github.com/liblaf/tangerine/issues
Project-URL: Release Notes, https://github.com/liblaf/tangerine/releases
Project-URL: Source Code, https://github.com/liblaf/tangerine
Author-email: liblaf <30631553+liblaf@users.noreply.github.com>
License-Expression: MIT
Classifier: Development Status :: 4 - Beta
Classifier: Intended Audience :: Developers
Classifier: License :: OSI Approved
Classifier: License :: OSI Approved :: MIT License
Classifier: Operating System :: OS Independent
Classifier: Programming Language :: Python
Classifier: Programming Language :: Python :: 3
Classifier: Programming Language :: Python :: 3.12
Classifier: Programming Language :: Python :: 3.13
Classifier: Typing :: Typed
Requires-Python: >=3.12
Requires-Dist: attrs<26,>=25
Requires-Dist: cappa<0.31,>=0.30
Requires-Dist: cytoolz<2,>=1
Requires-Dist: emoji>=2.14.1
Requires-Dist: githubkit<0.14,>=0.13
Requires-Dist: gitpython<4,>=3
Requires-Dist: jinja2<4,>=3
Requires-Dist: lazy-loader<0.5,>=0.4
Requires-Dist: liblaf-grapes<5,>=4
Requires-Dist: loguru<0.8,>=0.7
Requires-Dist: platformdirs<5,>=4
